loadlamb/.chalice/config.json
loadlamb/__init__.py
loadlamb/app.py
loadlamb/chalicelib/__init__.py
loadlamb/chalicelib/cli.py
loadlamb/chalicelib/contrib/__init__.py
loadlamb/chalicelib/contrib/db/__init__.py
loadlamb/chalicelib/contrib/db/loading.py
loadlamb/chalicelib/contrib/db/models.py
loadlamb/chalicelib/contrib/requests/__init__.py
loadlamb/chalicelib/contrib/requests/cognito.py
loadlamb/chalicelib/contrib/requests/django.py
loadlamb/chalicelib/contrib/requests/django_login.py
loadlamb/chalicelib/contrib/requests/login.py
loadlamb/chalicelib/contrib/requests/xmlrpc.py
loadlamb/chalicelib/lambdas.py
loadlamb/chalicelib/load.py
loadlamb/chalicelib/request.py
loadlamb/chalicelib/requirements.txt
loadlamb/chalicelib/response.py
loadlamb/chalicelib/sam.py
loadlamb/chalicelib/templates/extension.py.jinja2
loadlamb/chalicelib/templates/setup.py.jinja2
loadlamb/chalicelib/tests/__init__.py
loadlamb/chalicelib/tests/test_run.py
loadlamb/chalicelib/tests/test_utils.py
loadlamb/chalicelib/tests/wsgi/__init__.py
loadlamb/chalicelib/tests/wsgi/djangor/__init__.py
loadlamb/chalicelib/tests/wsgi/djangor/accounts/__init__.py
loadlamb/chalicelib/tests/wsgi/djangor/accounts/admin.py
loadlamb/chalicelib/tests/wsgi/djangor/accounts/apps.py
loadlamb/chalicelib/tests/wsgi/djangor/accounts/fixtures/users.yaml
loadlamb/chalicelib/tests/wsgi/djangor/accounts/migrations/__init__.py
loadlamb/chalicelib/tests/wsgi/djangor/accounts/models.py
loadlamb/chalicelib/tests/wsgi/djangor/accounts/tests.py
loadlamb/chalicelib/tests/wsgi/djangor/accounts/urls.py
loadlamb/chalicelib/tests/wsgi/djangor/accounts/views.py
loadlamb/chalicelib/tests/wsgi/djangor/djangor/__init__.py
loadlamb/chalicelib/tests/wsgi/djangor/djangor/settings.py
loadlamb/chalicelib/tests/wsgi/djangor/djangor/templates/base.html
loadlamb/chalicelib/tests/wsgi/djangor/djangor/templates/registration/login.html
loadlamb/chalicelib/tests/wsgi/djangor/djangor/templates/registration/user-detail.html
loadlamb-0.5.10.dist-info/entry_points.txt
loadlamb-0.5.10.dist-info/LICENSE
loadlamb-0.5.10.dist-info/WHEEL
loadlamb-0.5.10.dist-info/METADATA
loadlamb-0.5.10.dist-info/RECORD
