Metadata-Version: 2.1
Name: loadlamb
Version: 0.5.10
Summary: Load testing library built to run on AWS Lambda
License: BSD-3-Clause
Author: Brian Jinwright
Author-email: brian@ipoots.com
Requires-Python: >=3.6,<4.0
Classifier: License :: OSI Approved :: BSD License
Classifier: Programming Language :: Python :: 3
Classifier: Programming Language :: Python :: 3.6
Classifier: Programming Language :: Python :: 3.7
Requires-Dist: PyYAML (>=5.1,<6.0)
Requires-Dist: aiohttp (>=3.5,<4.0)
Requires-Dist: aiohttp_xmlrpc (>=0.7.4,<0.8.0)
Requires-Dist: base58 (>=1.0,<2.0)
Requires-Dist: beautifulsoup4 (>=4.7,<5.0)
Requires-Dist: boto3 (>=1.9,<2.0)
Requires-Dist: chalice (>=1.8,<2.0)
Requires-Dist: docb (>=1.1,<2.0)
Requires-Dist: jinja2 (>=2.10,<3.0)
Requires-Dist: python-slugify (>=3.0,<4.0)
Requires-Dist: requests (>=2.21,<3.0)
Requires-Dist: sammy (>=0.4.3,<0.5.0)
Requires-Dist: unipath (>=1.1,<2.0)
Requires-Dist: warrant-lite (>=1.0,<2.0)
